hasan_pkg/__init__.py
hasan_pkg/customer.py
hasan_pkg/classes/__init__.py
hasan_pkg/classes/customer.py
hasan_pkg/scripts/__init__.py
hasan_pkg/scripts/run_something.py
hasan_pkg_2/__init__.py
hasan_pkg_2/some_script.py
wheelsbyhasan-0.0.9.dist-info/LICENSE
wheelsbyhasan-0.0.9.dist-info/METADATA
wheelsbyhasan-0.0.9.dist-info/WHEEL
wheelsbyhasan-0.0.9.dist-info/top_level.txt
wheelsbyhasan-0.0.9.dist-info/RECORD
