Metadata-Version: 2.1
Name: wheelsbyhasan
Version: 0.0.9
Summary: Cool First Wheel
Home-page: UNKNOWN
Author: Hasan Abu-Rayyan
Author-email: hasanaburayyan21@gmail.com
License: UNKNOWN
Platform: UNKNOWN
Requires-Python: >=3.6
